klingon_serial/__init__.py
klingon_serial/generate.py
klingon_serial/strtobool.py
klingon_serial/utils.py
tests/__init__.py
tests/test_klingon_get_serial.py
tests/test_klingon_strtobool.py
tests/test_klingon_utils.py
klingon_serial-0.1.15.dist-info/LICENSE
klingon_serial-0.1.15.dist-info/METADATA
klingon_serial-0.1.15.dist-info/WHEEL
klingon_serial-0.1.15.dist-info/entry_points.txt
klingon_serial-0.1.15.dist-info/top_level.txt
klingon_serial-0.1.15.dist-info/RECORD
