Metadata-Version: 2.1
Name: klingon-serial
Version: 0.1.15
Summary: Get a globally unique serial
Home-page: https://github.com/djh00t/module_klingon_serial
Author: David Hooton
Author-email: klingon_serial+david@hooton.org
License: MIT
Classifier: Programming Language :: Python :: 3
Classifier: License :: OSI Approved :: MIT License
Classifier: Operating System :: OS Independent
Requires-Python: >=3.9
License-File: LICENSE
Requires-Dist: psutil
Requires-Dist: pytest >=6.0
Requires-Dist: str2bool
